py3o.formats-0.2-py2.7-nspkg.pth
py3o/formats/main.py
py3o/formats/__init__.py
py3o.formats-0.2.dist-info/DESCRIPTION.rst
py3o.formats-0.2.dist-info/top_level.txt
py3o.formats-0.2.dist-info/zip-safe
py3o.formats-0.2.dist-info/METADATA
py3o.formats-0.2.dist-info/RECORD
py3o.formats-0.2.dist-info/WHEEL
py3o.formats-0.2.dist-info/metadata.json
py3o.formats-0.2.dist-info/namespace_packages.txt
