Metadata-Version: 2.0
Name: py3o.formats
Version: 0.2
Summary: Formats declarations for py3o
Home-page: http://bitbucket.org/faide/py3o.formats
Author: Björn Ricks
Author-email: bjoern.ricks@gmail.com
License: MIT License
Keywords: py3o
Platform: UNKNOWN
Classifier: Programming Language :: Python
Classifier: Topic :: Internet :: WWW/HTTP :: HTTP Servers
Classifier: Topic :: Text Processing :: General
Classifier: Development Status :: 4 - Beta
Classifier: Intended Audience :: Developers
Classifier: License :: OSI Approved :: MIT License
Classifier: Operating System :: OS Independent
Requires-Dist: setuptools
